kolorz/__init__.py
kolorz/cli.py
kolorz/colors.py
kolorz/kolor.py
kolorz-0.2.5.dist-info/LICENSE
kolorz-0.2.5.dist-info/WHEEL
kolorz-0.2.5.dist-info/entry_points.txt
kolorz-0.2.5.dist-info/METADATA
kolorz-0.2.5.dist-info/RECORD
