Metadata-Version: 2.1
Name: kolorz
Version: 0.2.5
Summary: A fast, extensible, and kolorful python library to print colored output to the terminal
License: MIT
Author: dotzenith
Author-email: contact@danshu.co
Requires-Python: >=3.9,<4.0
Classifier: License :: OSI Approved :: MIT License
Classifier: Programming Language :: Python :: 3
Classifier: Programming Language :: Python :: 3.9
Classifier: Programming Language :: Python :: 3.10
Classifier: Programming Language :: Python :: 3.11
Requires-Dist: dotwiz (>=0.4.0,<0.5.0)
